odoo/addons/crm_lead_product/README.rst
odoo/addons/crm_lead_product/__init__.py
odoo/addons/crm_lead_product/__manifest__.py
odoo/addons/crm_lead_product/i18n/crm_lead_product.pot
odoo/addons/crm_lead_product/models/__init__.py
odoo/addons/crm_lead_product/models/crm_lead.py
odoo/addons/crm_lead_product/models/crm_lead_line.py
odoo/addons/crm_lead_product/readme/CONFIGURE.rst
odoo/addons/crm_lead_product/readme/CONTRIBUTORS.rst
odoo/addons/crm_lead_product/readme/DESCRIPTION.rst
odoo/addons/crm_lead_product/readme/USAGE.rst
odoo/addons/crm_lead_product/report/__init__.py
odoo/addons/crm_lead_product/report/crm_product_report.py
odoo/addons/crm_lead_product/report/crm_product_report_views.xml
odoo/addons/crm_lead_product/security/ir.model.access.csv
odoo/addons/crm_lead_product/static/description/icon.png
odoo/addons/crm_lead_product/static/description/index.html
odoo/addons/crm_lead_product/tests/__init__.py
odoo/addons/crm_lead_product/tests/test_crm_lead_line.py
odoo/addons/crm_lead_product/views/crm_lead_line_views.xml
odoo/addons/crm_lead_product/views/crm_lead_views.xml
odoo11_addon_crm_lead_product-11.0.1.0.0.99.dev5.dist-info/METADATA
odoo11_addon_crm_lead_product-11.0.1.0.0.99.dev5.dist-info/WHEEL
odoo11_addon_crm_lead_product-11.0.1.0.0.99.dev5.dist-info/top_level.txt
odoo11_addon_crm_lead_product-11.0.1.0.0.99.dev5.dist-info/RECORD
